detect_contamination/.gitkeep
detect_contamination/__init__.py
detect_contamination/__main__.py
detect_contamination/detect.py
detect_contamination/detect_contamination.py
detect_contamination/fragmentation.py
detect_contamination/graph.py
detect_contamination/index_builder.py
detect_contamination/seqtotax.py
detect_contamination/table.py
detect_contamination-0.1.9.dist-info/entry_points.txt
detect_contamination-0.1.9.dist-info/LICENSE
detect_contamination-0.1.9.dist-info/WHEEL
detect_contamination-0.1.9.dist-info/METADATA
detect_contamination-0.1.9.dist-info/RECORD
